nonebot_plugin_paper/__init__.py
nonebot_plugin_paper/command.py
nonebot_plugin_paper/config.py
nonebot_plugin_paper/utils.py
nonebot_plugin_paper/libs/__init__.py
nonebot_plugin_paper/libs/arxiv.py
nonebot_plugin_paper/libs/render/__init__.py
nonebot_plugin_paper/libs/render/dependency_manager.py
nonebot_plugin_paper/libs/render/html_render.py
nonebot_plugin_paper/libs/render/pillow_render.py
nonebot_plugin_paper/libs/render/plain_render.py
nonebot_plugin_paper/libs/render/skia_render.py
nonebot_plugin_paper-0.1.3.dist-info/METADATA
nonebot_plugin_paper-0.1.3.dist-info/WHEEL
nonebot_plugin_paper-0.1.3.dist-info/licenses/LICENSE
nonebot_plugin_paper-0.1.3.dist-info/RECORD
