Metadata-Version: 2.4
Name: nonebot-plugin-paper
Version: 0.1.3
Summary: build a world of open science.
Author-email: BalconyJH <balconyjh@gmail.com>
License:                     GNU GENERAL PUBLIC LICENSE
License-File: LICENSE
Classifier: Intended Audience :: Developers
Classifier: Programming Language :: Python
Classifier: Programming Language :: Python :: 3
Classifier: Programming Language :: Python :: 3.9
Classifier: Programming Language :: Python :: 3.10
Classifier: Programming Language :: Python :: 3.11
Classifier: Programming Language :: Python :: 3.12
Classifier: Programming Language :: Python :: 3.13
Classifier: Topic :: Software Development :: Libraries :: Python Modules
Requires-Python: <4.0,>=3.9
Requires-Dist: aioarxiv>=0.2.1
Requires-Dist: nonebot-plugin-alconna>=0.59.4
Requires-Dist: nonebot-plugin-apscheduler>=0.3.0
Requires-Dist: nonebot-plugin-localstore>=0.5.1
Requires-Dist: nonebot-plugin-uninfo>=0.9.0
Requires-Dist: nonebot-plugin-waiter>=0.8.1
Requires-Dist: nonebot2>=2.4.0
Requires-Dist: packaging>=24.2
Requires-Dist: strenum>=0.4.15; python_full_version < '3.11'
Provides-Extra: pillow
Requires-Dist: pillow>=11.0.0; extra == 'pillow'
Provides-Extra: playwright
Requires-Dist: nonebot-plugin-htmlrender>=0.6.2; extra == 'playwright'
Provides-Extra: sentry
Requires-Dist: nonebot-plugin-sentry>=2.0.0; extra == 'sentry'
Provides-Extra: skia
Requires-Dist: matplotlib<3.10,>=3.9; extra == 'skia'
Requires-Dist: skia-python>=134.0b12; extra == 'skia'
